whisper_at/__init__.py
whisper_at/__main__.py
whisper_at/at_post_processing.py
whisper_at/audio.py
whisper_at/decoding.py
whisper_at/model.py
whisper_at/timing.py
whisper_at/tokenizer.py
whisper_at/transcribe.py
whisper_at/triton_ops.py
whisper_at/utils.py
whisper_at/version.py
whisper_at/assets/class_labels_indices.csv
whisper_at/assets/gpt2.tiktoken
whisper_at/assets/label_name_dict.json
whisper_at/assets/mel_filters.npz
whisper_at/assets/multilingual.tiktoken
whisper_at/normalizers/__init__.py
whisper_at/normalizers/basic.py
whisper_at/normalizers/english.json
whisper_at/normalizers/english.py
whisper_at-0.5.dist-info/LICENSE
whisper_at-0.5.dist-info/LICENSE_OpenAI_Whisper
whisper_at-0.5.dist-info/METADATA
whisper_at-0.5.dist-info/WHEEL
whisper_at-0.5.dist-info/entry_points.txt
whisper_at-0.5.dist-info/top_level.txt
whisper_at-0.5.dist-info/RECORD
