Metadata-Version: 2.1
Name: whisper-at
Version: 0.5
Summary: Joint speech recognition and audio tagging model.
Home-page: https://github.com/YuanGongND/whisper-at
Author: Yuan Gong
License: BSD
Requires-Python: >=3.8
License-File: LICENSE
License-File: LICENSE_OpenAI_Whisper
Requires-Dist: triton ==2.0.0
Requires-Dist: numba
Requires-Dist: numpy
Requires-Dist: torch
Requires-Dist: tqdm
Requires-Dist: more-itertools
Requires-Dist: tiktoken ==0.3.3
Provides-Extra: dev
Requires-Dist: pytest ; extra == 'dev'
Requires-Dist: scipy ; extra == 'dev'
Requires-Dist: black ; extra == 'dev'
Requires-Dist: flake8 ; extra == 'dev'
Requires-Dist: isort ; extra == 'dev'
